sqlalchemy_omopcdm/__init__.py
sqlalchemy_omopcdm/omopcdm54.py
sqlalchemy_omopcdm/py.typed
sqlalchemy_omopcdm-0.2.0.dist-info/LICENSE.txt
sqlalchemy_omopcdm-0.2.0.dist-info/METADATA
sqlalchemy_omopcdm-0.2.0.dist-info/WHEEL
sqlalchemy_omopcdm-0.2.0.dist-info/top_level.txt
sqlalchemy_omopcdm-0.2.0.dist-info/RECORD
