Metadata-Version: 2.1
Name: sqlalchemy-omopcdm
Version: 0.2.0
Summary: OMOP CDM v5.4 SQLAlchemy Declarative Mapping Models
Author-email: edenceHealth NV <info@edence.health>, Ben Burke <ben.burke@edence.health>
License: Apache License
Project-URL: Documentation, https://github.com/edencehealth/sqlalchemy_omopcdm
Project-URL: Source, https://github.com/edencehealth/sqlalchemy_omopcdm
Project-URL: Tracker, https://github.com/edencehealth/sqlalchemy_omopcdm/issues
Keywords: OHDSI,OMOP CDM,OMOP,CDM,SQLAlchemy,Models,Tables
Classifier: Programming Language :: Python :: 3
Classifier: License :: OSI Approved :: Apache Software License
Classifier: Operating System :: OS Independent
Requires-Python: >=3.11
License-File: LICENSE.txt
Requires-Dist: sqlalchemy >=2.0.0
